alibabacloud_datahub20240620/__init__.py
alibabacloud_datahub20240620/client.py
alibabacloud_datahub20240620/models/__init__.py
alibabacloud_datahub20240620/models/_get_connector_request.py
alibabacloud_datahub20240620/models/_get_connector_response.py
alibabacloud_datahub20240620/models/_get_connector_response_body.py
alibabacloud_datahub20240620/models/_get_group_request.py
alibabacloud_datahub20240620/models/_get_group_response.py
alibabacloud_datahub20240620/models/_get_group_response_body.py
alibabacloud_datahub20240620/models/_get_project_request.py
alibabacloud_datahub20240620/models/_get_project_response.py
alibabacloud_datahub20240620/models/_get_project_response_body.py
alibabacloud_datahub20240620/models/_get_records_request.py
alibabacloud_datahub20240620/models/_get_records_response.py
alibabacloud_datahub20240620/models/_get_records_response_body.py
alibabacloud_datahub20240620/models/_get_schema_request.py
alibabacloud_datahub20240620/models/_get_schema_response.py
alibabacloud_datahub20240620/models/_get_schema_response_body.py
alibabacloud_datahub20240620/models/_get_subscription_request.py
alibabacloud_datahub20240620/models/_get_subscription_response.py
alibabacloud_datahub20240620/models/_get_subscription_response_body.py
alibabacloud_datahub20240620/models/_get_topic_request.py
alibabacloud_datahub20240620/models/_get_topic_response.py
alibabacloud_datahub20240620/models/_get_topic_response_body.py
alibabacloud_datahub20240620/models/_list_connectors_request.py
alibabacloud_datahub20240620/models/_list_connectors_response.py
alibabacloud_datahub20240620/models/_list_connectors_response_body.py
alibabacloud_datahub20240620/models/_list_groups_request.py
alibabacloud_datahub20240620/models/_list_groups_response.py
alibabacloud_datahub20240620/models/_list_groups_response_body.py
alibabacloud_datahub20240620/models/_list_projects_request.py
alibabacloud_datahub20240620/models/_list_projects_response.py
alibabacloud_datahub20240620-1.2.0.dist-info/LICENSE
alibabacloud_datahub20240620-1.2.0.dist-info/METADATA
alibabacloud_datahub20240620-1.2.0.dist-info/WHEEL
alibabacloud_datahub20240620-1.2.0.dist-info/top_level.txt
alibabacloud_datahub20240620-1.2.0.dist-info/RECORD
